forklift-device/gpio-control/src/event_logger.v
module event_logger (
    input  wire        clk,
    input  wire        rst_n,

    /*
     * event_detector 출력
     */
    input  wire        event_valid,
    input  wire [7:0]  event_code,
    input  wire [7:0]  event_detail,

    /*
     * 이벤트 발생 시점
     */
    input  wire [31:0] timestamp_ms,

    /*
     * 현재 상태 snapshot
     */
    input  wire [1:0]  effective_risk,
    input  wire [2:0]  warning_state,

    input  wire        estop_active,
    input  wire        comm_error,
    input  wire        latch_active,

    input  wire        checksum_error_latched,
    input  wire        protocol_error_latched,
    input  wire        timeout_error_latched,

    input  wire        self_test_active,

    /*
     * 논리적인 실제 출력 상태
     * active-low 반전 전의 값 사용
     */
    input  wire [1:0]  led_active_pattern,
    input  wire        buzzer_active,

    /*
     * 이후 CLEAR_LOG 명령에 연결
     */
    input  wire        clear_log_req,

    /*
     * 조회 포트
     *
     * read_index 0은 항상 가장 오래된 이벤트
     */
    input  wire [3:0]  read_index,

    output reg  [63:0] read_data,
    output reg         read_valid,

    /*
     * 현재 저장된 이벤트 개수
     */
    output reg  [4:0]  log_count,

    /*
     * 다음 이벤트가 기록될 물리 주소
     */
    output reg  [3:0]  write_pointer,

    output wire        log_full
);

    /*
     * 16-entry × 64-bit
     */
    reg [63:0] event_memory [0:15];

    wire [63:0] current_event_record;

    /*
     * 64비트 이벤트 레코드 생성
     */
    assign current_event_record = {
        1'b0,                       // [63] reserved
        buzzer_active,              // [62]
        led_active_pattern,         // [61:60]
        self_test_active,           // [59]
        timeout_error_latched,      // [58]
        protocol_error_latched,     // [57]
        checksum_error_latched,     // [56]
        latch_active,               // [55]
        comm_error,                 // [54]
        estop_active,               // [53]
        warning_state,              // [52:50]
        effective_risk,             // [49:48]
        event_detail,               // [47:40]
        event_code,                 // [39:32]
        timestamp_ms                // [31:0]
    };

    assign log_full =
        (log_count == 5'd16);

    /*
     * 이벤트 기록
     *
     * write_pointer는 다음 기록 위치를 가리킨다.
     * 로그가 가득 차면 가장 오래된 항목부터 덮어쓴다.
     */
    always @(posedge clk or negedge rst_n) begin
        if (!rst_n) begin
            write_pointer <= 4'd0;
            log_count     <= 5'd0;
        end
        else if (clear_log_req) begin
            /*
             * 메모리 비트를 실제로 0으로 지우지 않고
             * 포인터와 개수만 초기화한다.
             *
             * count가 0이므로 기존 데이터는 유효하지 않다.
             */
            write_pointer <= 4'd0;
            log_count     <= 5'd0;
        end
        else if (event_valid) begin
            event_memory[write_pointer]
                <= current_event_record;

            /*
             * 4비트이므로 15 다음에는 자동으로 0
             */
            write_pointer <= write_pointer + 1'b1;

            if (log_count < 5'd16)
                log_count <= log_count + 1'b1;
            else
                log_count <= 5'd16;
        end
    end

    /*
     * read_index는 물리 주소가 아니라
     * 시간순 논리 index이다.
     *
     * read_index 0:
     * 가장 오래된 이벤트
     *
     * read_index log_count-1:
     * 가장 최근 이벤트
     */
    reg [3:0] physical_read_index;

    always @(*) begin
        read_data           = 64'd0;
        read_valid          = 1'b0;
        physical_read_index = 4'd0;

        if (read_index < log_count) begin
            read_valid = 1'b1;

            /*
             * 아직 한 번도 가득 차지 않은 경우
             * 메모리 0번부터 시간순으로 저장되어 있다.
             */
            if (log_count < 5'd16) begin
                physical_read_index = read_index;
            end

            /*
             * 로그가 가득 찬 경우 write_pointer는
             * 다음에 덮어쓸 가장 오래된 항목을 가리킨다.
             *
             * 4비트 덧셈이므로 15를 넘으면 자동 wrap.
             */
            else begin
                physical_read_index =
                    write_pointer + read_index;
            end

            read_data =
                event_memory[physical_read_index];
        end
    end

endmodule

forklift-device/gpio-control/src/tb_event_logger.v
`timescale 1ns / 1ps

module tb_event_logger;

    reg clk;
    reg rst_n;

    reg        event_valid;
    reg [7:0]  event_code;
    reg [7:0]  event_detail;
    reg [31:0] timestamp_ms;

    reg [1:0] effective_risk;
    reg [2:0] warning_state;

    reg estop_active;
    reg comm_error;
    reg latch_active;

    reg checksum_error_latched;
    reg protocol_error_latched;
    reg timeout_error_latched;

    reg self_test_active;

    reg [1:0] led_active_pattern;
    reg       buzzer_active;

    reg       clear_log_req;
    reg [3:0] read_index;

    wire [63:0] read_data;
    wire        read_valid;

    wire [4:0] log_count;
    wire [3:0] write_pointer;
    wire       log_full;

    event_logger dut (
        .clk                    (clk),
        .rst_n                  (rst_n),

        .event_valid            (event_valid),
        .event_code             (event_code),
        .event_detail           (event_detail),

        .timestamp_ms           (timestamp_ms),

        .effective_risk         (effective_risk),
        .warning_state          (warning_state),

        .estop_active           (estop_active),
        .comm_error             (comm_error),
        .latch_active           (latch_active),

        .checksum_error_latched (checksum_error_latched),
        .protocol_error_latched (protocol_error_latched),
        .timeout_error_latched  (timeout_error_latched),

        .self_test_active       (self_test_active),

        .led_active_pattern     (led_active_pattern),
        .buzzer_active          (buzzer_active),

        .clear_log_req          (clear_log_req),

        .read_index             (read_index),
        .read_data              (read_data),
        .read_valid             (read_valid),

        .log_count              (log_count),
        .write_pointer          (write_pointer),
        .log_full               (log_full)
    );

    initial begin
        clk = 1'b0;
        forever #5 clk = ~clk;
    end

    task push_event;
        input [7:0]  code;
        input [7:0]  detail;
        input [31:0] timestamp;
        begin
            @(negedge clk);

            event_code  = code;
            event_detail = detail;
            timestamp_ms = timestamp;
            event_valid = 1'b1;

            @(negedge clk);

            event_valid = 1'b0;
        end
    endtask

    task print_log;
        input [3:0] index;
        begin
            read_index = index;
            #1;

            if (read_valid) begin
                $display(
                    "index=%0d timestamp=%0d code=%02X detail=%02X",
                    index,
                    read_data[31:0],
                    read_data[39:32],
                    read_data[47:40]
                );
            end
            else begin
                $display(
                    "index=%0d invalid",
                    index
                );
            end
        end
    endtask

    integer i;

    initial begin
        $dumpfile("event_logger.vcd");
        $dumpvars(0, tb_event_logger);

        rst_n = 1'b0;

        event_valid  = 1'b0;
        event_code   = 8'd0;
        event_detail = 8'd0;
        timestamp_ms = 32'd0;

        effective_risk = 2'd0;
        warning_state  = 3'd0;

        estop_active = 1'b0;
        comm_error   = 1'b0;
        latch_active = 1'b0;

        checksum_error_latched = 1'b0;
        protocol_error_latched = 1'b0;
        timeout_error_latched  = 1'b0;

        self_test_active = 1'b0;

        led_active_pattern = 2'b00;
        buzzer_active      = 1'b0;

        clear_log_req = 1'b0;
        read_index    = 4'd0;

        #30;
        rst_n = 1'b1;

        /*
         * 세 이벤트 저장
         */
        push_event(8'h06, 8'h00, 32'd100);
        push_event(8'h09, 8'h02, 32'd200);
        push_event(8'h02, 8'h00, 32'd300);

        #10;

        $display(
            "log_count=%0d write_pointer=%0d",
            log_count,
            write_pointer
        );

        print_log(0);
        print_log(1);
        print_log(2);
        print_log(3);

        /*
         * 총 18개가 되도록 추가 저장
         * 가장 오래된 2개는 덮어써져야 한다.
         */
        for (i = 4; i <= 18; i = i + 1) begin
            push_event(
                i[7:0],
                8'h00,
                i * 100
            );
        end

        #10;

        $display(
            "after overflow: count=%0d pointer=%0d full=%0d",
            log_count,
            write_pointer,
            log_full
        );

        /*
         * index 0은 덮어쓰기 후 가장 오래된 이벤트
         */
        print_log(0);
        print_log(15);

        /*
         * 로그 초기화
         */
        @(negedge clk);
        clear_log_req = 1'b1;

        @(negedge clk);
        clear_log_req = 1'b0;

        #10;

        $display(
            "after clear: count=%0d pointer=%0d",
            log_count,
            write_pointer
        );

        print_log(0);

        #20;
        $finish;
    end

endmodule

forklift-device/gpio-control/src/event_logger.vcd
$date
	Wed Jul 22 18:13:07 2026
$end
$version
	Icarus Verilog
$end
$timescale
	1ps
$end
$scope module tb_event_logger $end
$var wire 4 ! write_pointer [3:0] $end
$var wire 1 " read_valid $end
$var wire 64 # read_data [63:0] $end
$var wire 1 $ log_full $end
$var wire 5 % log_count [4:0] $end
$var reg 1 & buzzer_active $end
$var reg 1 ' checksum_error_latched $end
$var reg 1 ( clear_log_req $end
$var reg 1 ) clk $end
$var reg 1 * comm_error $end
$var reg 2 + effective_risk [1:0] $end
$var reg 1 , estop_active $end
$var reg 8 - event_code [7:0] $end
$var reg 8 . event_detail [7:0] $end
$var reg 1 / event_valid $end
$var reg 1 0 latch_active $end
$var reg 2 1 led_active_pattern [1:0] $end
$var reg 1 2 protocol_error_latched $end
$var reg 4 3 read_index [3:0] $end
$var reg 1 4 rst_n $end
$var reg 1 5 self_test_active $end
$var reg 1 6 timeout_error_latched $end
$var reg 32 7 timestamp_ms [31:0] $end
$var reg 3 8 warning_state [2:0] $end
$var integer 32 9 i [31:0] $end
$scope module dut $end
$var wire 1 & buzzer_active $end
$var wire 1 ' checksum_error_latched $end
$var wire 1 ( clear_log_req $end
$var wire 1 ) clk $end
$var wire 1 * comm_error $end
$var wire 2 : effective_risk [1:0] $end
$var wire 1 , estop_active $end
$var wire 8 ; event_code [7:0] $end
$var wire 8 < event_detail [7:0] $end
$var wire 1 / event_valid $end
$var wire 1 0 latch_active $end
$var wire 2 = led_active_pattern [1:0] $end
$var wire 1 2 protocol_error_latched $end
$var wire 4 > read_index [3:0] $end
$var wire 1 4 rst_n $end
$var wire 1 5 self_test_active $end
$var wire 1 6 timeout_error_latched $end
$var wire 32 ? timestamp_ms [31:0] $end
$var wire 3 @ warning_state [2:0] $end
$var wire 1 $ log_full $end
$var wire 64 A current_event_record [63:0] $end
$var reg 5 B log_count [4:0] $end
$var reg 4 C physical_read_index [3:0] $end
$var reg 64 D read_data [63:0] $end
$var reg 1 " read_valid $end
$var reg 4 E write_pointer [3:0] $end
$upscope $end
$scope task print_log $end
$var reg 4 F index [3:0] $end
$upscope $end
$scope task push_event $end
$var reg 8 G code [7:0] $end
$var reg 8 H detail [7:0] $end
$var reg 32 I timestamp [31:0] $end
$upscope $end
$upscope $end
$enddefinitions $end
$comment Show the parameter values. $end
$dumpall
$end
#0
$dumpvars
bx I
bx H
bx G
bx F
b0 E
b0 D
b0 C
b0 B
b0 A
b0 @
b0 ?
b0 >
b0 =
b0 <
b0 ;
b0 :
bx 9
b0 8
b0 7
06
05
04
b0 3
02
b0 1
00
0/
b0 .
b0 -
0,
b0 +
0*
0)
0(
0'
0&
b0 %
0$
b0 #
0"
b0 !
$end
#5000
1)
#10000
0)
#15000
1)
#20000
0)
#25000
1)
#30000
1/
b1100100 7
b1100100 ?
b11000000000000000000000000001100100 A
b110 -
b110 ;
0)
b1100100 I
b0 H
b110 G
14
#35000
b11000000000000000000000000001100100 #
b11000000000000000000000000001100100 D
1"
b1 %
b1 B
b1 !
b1 E
1)
#40000
b11001000 I
b10 H
b1001 G
0/
0)
#45000
1)
#50000
1/
b11001000 7
b11001000 ?
b10 .
b10 <
b100000100100000000000000000000000011001000 A
b1001 -
b1001 ;
0)
#55000
1"
b11000000000000000000000000001100100 #
b11000000000000000000000000001100100 D
b10 %
b10 B
b10 !
b10 E
1)
#60000
b100101100 I
b0 H
b10 G
0/
0)
#65000
1)
#70000
1/
b100101100 7
b100101100 ?
b0 .
b0 <
b1000000000000000000000000100101100 A
b10 -
b10 ;
0)
#75000
1"
b11000000000000000000000000001100100 #
b11000000000000000000000000001100100 D
b11 %
b11 B
b11 !
b11 E
1)
#80000
0/
0)
#85000
1)
#90000
0)
b0 F
#91000
b1 C
1"
b100000100100000000000000000000000011001000 #
b100000100100000000000000000000000011001000 D
b1 3
b1 >
b1 F
#92000
b10 C
1"
b1000000000000000000000000100101100 #
b1000000000000000000000000100101100 D
b10 3
b10 >
b10 F
#93000
b0 C
0"
b0 #
b0 D
b11 3
b11 >
b11 F
#94000
b110010000 I
b100 G
b100 9
#95000
1)
#100000
1/
b110010000 7
b110010000 ?
b10000000000000000000000000110010000 A
b100 -
b100 ;
0)
#105000
b10000000000000000000000000110010000 #
b10000000000000000000000000110010000 D
b11 C
1"
b100 %
b100 B
b100 !
b100 E
1)
#110000
b111110100 I
b101 G
b101 9
0/
0)
#115000
1)
#120000
1/
b111110100 7
b111110100 ?
b10100000000000000000000000111110100 A
b101 -
b101 ;
0)
#125000
b11 C
1"
b10000000000000000000000000110010000 #
b10000000000000000000000000110010000 D
b101 %
b101 B
b101 !
b101 E
1)
#130000
b1001011000 I
b110 G
b110 9
0/
0)
#135000
1)
#140000
1/
b1001011000 7
b1001011000 ?
b11000000000000000000000001001011000 A
b110 -
b110 ;
0)
#145000
b11 C
1"
b10000000000000000000000000110010000 #
b10000000000000000000000000110010000 D
b110 %
b110 B
b110 !
b110 E
1)
#150000
b1010111100 I
b111 G
b111 9
0/
0)
#155000
1)
#160000
1/
b1010111100 7
b1010111100 ?
b11100000000000000000000001010111100 A
b111 -
b111 ;
0)
#165000
b11 C
1"
b10000000000000000000000000110010000 #
b10000000000000000000000000110010000 D
b111 %
b111 B
b111 !
b111 E
1)
#170000
b1100100000 I
b1000 G
b1000 9
0/
0)
#175000
1)
#180000
1/
b1100100000 7
b1100100000 ?
b100000000000000000000000001100100000 A
b1000 -
b1000 ;
0)
#185000
b11 C
1"
b10000000000000000000000000110010000 #
b10000000000000000000000000110010000 D
b1000 %
b1000 B
b1000 !
b1000 E
1)
#190000
b1110000100 I
b1001 G
b1001 9
0/
0)
#195000
1)
#200000
1/
b1110000100 7
b1110000100 ?
b100100000000000000000000001110000100 A
b1001 -
b1001 ;
0)
#205000
b11 C
1"
b10000000000000000000000000110010000 #
b10000000000000000000000000110010000 D
b1001 %
b1001 B
b1001 !
b1001 E
1)
#210000
b1111101000 I
b1010 G
b1010 9
0/
0)
#215000
1)
#220000
1/
b1111101000 7
b1111101000 ?
b101000000000000000000000001111101000 A
b1010 -
b1010 ;
0)
#225000
b11 C
1"
b10000000000000000000000000110010000 #
b10000000000000000000000000110010000 D
b1010 %
b1010 B
b1010 !
b1010 E
1)
#230000
b10001001100 I
b1011 G
b1011 9
0/
0)
#235000
1)
#240000
1/
b10001001100 7
b10001001100 ?
b101100000000000000000000010001001100 A
b1011 -
b1011 ;
0)
#245000
b11 C
1"
b10000000000000000000000000110010000 #
b10000000000000000000000000110010000 D
b1011 %
b1011 B
b1011 !
b1011 E
1)
#250000
b10010110000 I
b1100 G
b1100 9
0/
0)
#255000
1)
#260000
1/
b10010110000 7
b10010110000 ?
b110000000000000000000000010010110000 A
b1100 -
b1100 ;
0)
#265000
b11 C
1"
b10000000000000000000000000110010000 #
b10000000000000000000000000110010000 D
b1100 %
b1100 B
b1100 !
b1100 E
1)
#270000
b10100010100 I
b1101 G
b1101 9
0/
0)
#275000
1)
#280000
1/
b10100010100 7
b10100010100 ?
b110100000000000000000000010100010100 A
b1101 -
b1101 ;
0)
#285000
b11 C
1"
b10000000000000000000000000110010000 #
b10000000000000000000000000110010000 D
b1101 %
b1101 B
b1101 !
b1101 E
1)
#290000
b10101111000 I
b1110 G
b1110 9
0/
0)
#295000
1)
#300000
1/
b10101111000 7
b10101111000 ?
b111000000000000000000000010101111000 A
b1110 -
b1110 ;
0)
#305000
b11 C
1"
b10000000000000000000000000110010000 #
b10000000000000000000000000110010000 D
b1110 %
b1110 B
b1110 !
b1110 E
1)
#310000
b10111011100 I
b1111 G
b1111 9
0/
0)
#315000
1)
#320000
1/
b10111011100 7
b10111011100 ?
b111100000000000000000000010111011100 A
b1111 -
b1111 ;
0)
#325000
b11 C
1"
b10000000000000000000000000110010000 #
b10000000000000000000000000110010000 D
b1111 %
b1111 B
b1111 !
b1111 E
1)
#330000
b11001000000 I
b10000 G
b10000 9
0/
0)
#335000
1)
#340000
1/
b11001000000 7
b11001000000 ?
b1000000000000000000000000011001000000 A
b10000 -
b10000 ;
0)
#345000
b11 C
1"
b10000000000000000000000000110010000 #
b10000000000000000000000000110010000 D
1$
b10000 %
b10000 B
b0 !
b0 E
1)
#350000
b11010100100 I
b10001 G
b10001 9
0/
0)
#355000
1)
#360000
1/
b11010100100 7
b11010100100 ?
b1000100000000000000000000011010100100 A
b10001 -
b10001 ;
0)
#365000
b100 C
1"
b10100000000000000000000000111110100 #
b10100000000000000000000000111110100 D
b1 !
b1 E
1)
#370000
b11100001000 I
b10010 G
b10010 9
0/
0)
#375000
1)
#380000
1/
b11100001000 7
b11100001000 ?
b1001000000000000000000000011100001000 A
b10010 -
b10010 ;
0)
#385000
b101 C
1"
b11000000000000000000000001001011000 #
b11000000000000000000000001001011000 D
b10 !
b10 E
1)
#390000
b10011 9
0/
0)
#395000
1)
#400000
b10 C
1"
b1000000000000000000000000100101100 #
b1000000000000000000000000100101100 D
0)
b0 3
b0 >
b0 F
#401000
b1 C
1"
b1001000000000000000000000011100001000 #
b1001000000000000000000000011100001000 D
b1111 3
b1111 >
b1111 F
#405000
1)
#410000
1(
0)
#415000
b0 C
0"
b0 #
b0 D
0$
b0 %
b0 B
b0 !
b0 E
1)
#420000
0(
0)
#425000
1)
#430000
0)
b0 3
b0 >
b0 F
